tornado_request_mapping/__init__.py
tornado_request_mapping-0.0.6.dist-info/METADATA
tornado_request_mapping-0.0.6.dist-info/WHEEL
tornado_request_mapping-0.0.6.dist-info/top_level.txt
tornado_request_mapping-0.0.6.dist-info/RECORD
