Metadata-Version: 2.1
Name: tornado-request-mapping
Version: 0.0.6
Summary: spring-like request_mapping for tornado.
Home-page: https://github.com/sazima/tornado_request_mapping
Author: wukt
Author-email: w@wktadmin.com
License: UNKNOWN
Platform: UNKNOWN
Classifier: Programming Language :: Python :: 3
Classifier: License :: OSI Approved :: MIT License
Classifier: Operating System :: OS Independent
Requires-Dist: tornado
